mcp_mt5/__init__.py
mcp_mt5/main.py
mcp_mt5/test_client.py
mcp_metatrader5_server-0.1.7.dist-info/METADATA
mcp_metatrader5_server-0.1.7.dist-info/WHEEL
mcp_metatrader5_server-0.1.7.dist-info/entry_points.txt
mcp_metatrader5_server-0.1.7.dist-info/RECORD
