Metadata-Version: 2.4
Name: mcp-metatrader5-server
Version: 0.1.7
Summary: A Model Context Protocol (MCP) server for MetaTrader 5
Project-URL: Homepage, https://github.com/Qoyyuum/mcp-metatrader5-server
Project-URL: Bug Tracker, https://github.com/Qoyyuum/mcp-metatrader5-server/issues
Project-URL: Documentation, https://mcp-metatrader5-server.readthedocs.io
Author: Abdul Qoyyuum
Classifier: Development Status :: 4 - Beta
Classifier: Intended Audience :: Financial and Insurance Industry
Classifier: License :: OSI Approved :: MIT License
Classifier: Operating System :: OS Independent
Classifier: Programming Language :: Python :: 3
Classifier: Topic :: Office/Business :: Financial :: Investment
Requires-Python: >=3.11
Requires-Dist: fastmcp==2.12.5
Requires-Dist: metatrader5==5.0.5370
Requires-Dist: pandas>=2.3.3
Requires-Dist: pydantic>=2.11.9
Requires-Dist: python-dotenv>=1.1.1
Provides-Extra: docs
Requires-Dist: mkdocs-autorefs>=0.5.0; extra == 'docs'
Requires-Dist: mkdocs-material>=9.5.0; extra == 'docs'
Requires-Dist: mkdocs>=1.5.3; extra == 'docs'
Requires-Dist: pymdown-extensions>=10.7; extra == 'docs'
